Workbook

Sheet lawyers
A1: lawyer_id | B1: lawyer_name | C1: level | D1: standard_hourly_rate | E1: cost_per_hour | F1: practice_area_id
A2: 1 | B2: Raj Partner | C2: Partner | D2: 15000 | E2: 8000 | F2: 1
A3: 2 | B3: Anita Partner | C3: Partner | D3: 14000 | E3: 7500 | F3: 2
A4: 3 | B4: Vivek Senior | C4: Senior | D4: 10000 | E4: 5000 | F4: 1
A5: 4 | B5: Meera Senior | C5: Senior | D5: 9500 | E5: 4800 | F5: 3
A6: 5 | B6: Arjun Junior | C6: Junior | D6: 6000 | E6: 3000 | F6: 2
A7: 6 | B7: Neha Junior | C7: Junior | D7: 5500 | E7: 2800 | F7: 4

Sheet practice_areas
A1: practice_area_id | B1: practice_name
A2: 1 | B2: Litigation
A3: 2 | B3: Corporate
A4: 3 | B4: Tax
A5: 4 | B5: Intellectual Property

Sheet clients
A1: client_id | B1: client_name | C1: client_type
A2: 1 | B2: ABC Industries | C2: Corporate
A3: 2 | B3: Zenith Holdings | C3: Corporate
A4: 3 | B4: Sharma Enterprises | C4: SME
A5: 4 | B5: Global Retail Ltd | C5: Corporate
A6: 5 | B6: Ramesh Kumar | C6: Individual

Sheet matters
A1: matter_id | B1: client_id | C1: practice_area_id | D1: matter_name | E1: start_date
A2: 1 | B2: 1 | C2: 1 | D2: ABC Litigation Case | E2: 45292
A3: 2 | B3: 1 | C3: 3 | D3: ABC Tax Advisory | E3: 15-02-2024
A4: 3 | B4: 2 | C4: 2 | D4: Zenith M&A Deal | E4: 45568
A5: 4 | B5: 3 | C5: 1 | D5: Sharma Dispute | E5: 45416
A6: 5 | B6: 4 | C6: 4 | D6: Global IP Filing | E6: 20-05-2024
A7: 6 | B7: 5 | C7: 3 | D7: Ramesh Tax Notice | E7: 45297

Sheet time_entries
A1: time_entry_id | B1: matter_id | C1: lawyer_id | D1: work_date | E1: hours_worked | F1: billed_amount | G1: client_id
A2: 1 | B2: 1 | C2: 1 | D2: 45413 | E2: 5 | F2: =E2 * VLOOKUP(C2, lawyers!A:F, 4, FALSE) -> 75000 | G2: =VLOOKUP(B2, matters!A:B, 2, FALSE) -> 1
A3: 2 | B3: 1 | C3: 3 | D3: 45444 | E3: 8 | F3: =E3 * VLOOKUP(C3, lawyers!A:F, 4, FALSE) -> 80000 | G3: =VLOOKUP(B3, matters!A:B, 2, FALSE) -> 1
A4: 3 | B4: 2 | C4: 4 | D4: 18-02-2024 | E4: 6 | F4: =E4 * VLOOKUP(C4, lawyers!A:F, 4, FALSE) -> 57000 | G4: =VLOOKUP(B4, matters!A:B, 2, FALSE) -> 1
A5: 4 | B5: 3 | C5: 2 | D5: 45629 | E5: 10 | F5: =E5 * VLOOKUP(C5, lawyers!A:F, 4, FALSE) -> 140000 | G5: =VLOOKUP(B5, matters!A:B, 2, FALSE) -> 2
A6: 5 | B6: 3 | C6: 5 | D6: 13-03-2024 | E6: 7 | F6: =E6 * VLOOKUP(C6, lawyers!A:F, 4, FALSE) -> 42000 | G6: =VLOOKUP(B6, matters!A:B, 2, FALSE) -> 2
A7: 6 | B7: 4 | C7: 3 | D7: 45477 | E7: 4 | F7: =E7 * VLOOKUP(C7, lawyers!A:F, 4, FALSE) -> 40000 | G7: =VLOOKUP(B7, matters!A:B, 2, FALSE) -> 3
A8: 7 | B8: 5 | C8: 6 | D8: 22-05-2024 | E8: 9 | F8: =E8 * VLOOKUP(C8, lawyers!A:F, 4, FALSE) -> 49500 | G8: =VLOOKUP(B8, matters!A:B, 2, FALSE) -> 4
A9: 8 | B9: 6 | C9: 4 | D9: 45328 | E9: 3 | F9: =E9 * VLOOKUP(C9, lawyers!A:F, 4, FALSE) -> 28500 | G9: =VLOOKUP(B9, matters!A:B, 2, FALSE) -> 5

Sheet billing_adjustments
A1: adjustment_id | B1: matter_id | C1: adjustment_type | D1: adjustment_amount | E1: client_id
A2: 1 | B2: 1 | C2: Write-off | D2: -20000 | E2: =VLOOKUP(B2, matters!A:B, 2, FALSE) -> 1
A3: 2 | B3: 2 | C3: Write-off | D3: -10000 | E3: =VLOOKUP(B3, matters!A:B, 2, FALSE) -> 1
A4: 3 | B4: 3 | C4: Write-off | D4: -30000 | E4: =VLOOKUP(B4, matters!A:B, 2, FALSE) -> 2
A5: 4 | B5: 4 | C5: Write-up | D5: 5000 | E5: =VLOOKUP(B5, matters!A:B, 2, FALSE) -> 3
A6: 5 | B6: 5 | C6: Write-off | D6: -15000 | E6: =VLOOKUP(B6, matters!A:B, 2, FALSE) -> 4

Sheet collections
A1: collection_id | B1: matter_id | C1: amount_collected | D1: collection_date | E1: client_id
A2: 1 | B2: 1 | C2: 55000 | D2: 15-01-2024 | E2: =VLOOKUP(B2, matters!A:B, 2, FALSE) -> 1
A3: 2 | B3: 2 | C3: 45000 | D3: 28-02-2024 | E3: =VLOOKUP(B3, matters!A:B, 2, FALSE) -> 1
A4: 3 | B4: 3 | C4: 100000 | D4: 30-03-2024 | E4: =VLOOKUP(B4, matters!A:B, 2, FALSE) -> 2
A5: 4 | B5: 4 | C5: 35000 | D5: 20-04-2024 | E5: =VLOOKUP(B5, matters!A:B, 2, FALSE) -> 3
A6: 5 | B6: 5 | C6: 30000 | D6: 45418 | E6: =VLOOKUP(B6, matters!A:B, 2, FALSE) -> 4
A7: 6 | B7: 6 | C7: 15000 | D7: 15-06-2024 | E7: =VLOOKUP(B7, matters!A:B, 2, FALSE) -> 5

Sheet analysis
A1: KPI | B1: Value
A2: Total Billed Revenue | B2: =SUM(time_entries!F:F) -> 512000
A3: Total Adjustments | B3: =SUM(billing_adjustments!D:D) -> -70000
A4: Adjusted Revenue | B4: =B2 + B3 -> 442000
A5: Total Collected Revenue | B5: =SUM(collections!C:C) -> 280000
A6: Billing Realization % | B6: =B4 / B2 -> 0.86328125
A7: Collection Realization % | B7: =B5 / B4 -> 0.63348416
A8: Overall Realization % | B8: =B5 / B2 -> 0.546875
A9: Revenue Lost Due to Adjustments | B9: =ABS(B3) -> 70000
A10: Revenue Not Collected | B10: =B4 - B5 -> 162000
A13: Client | B13: Client_ID | C13: Billed Revenue | D13: Adjusted Revenue | E13: Collected Revenue | F13: Overall Realization % | G13: Discount Loss | H13: Collection Loss | I13: Discount % | J13: Collection Gap % | K13: Risk Level | L13: Target Realization
A14: ABC Industries | B14: 1 | C14: =SUMIF(time_entries!G:G, B14, time_entries!F:F) -> 212000 | D14: =C14 + SUMIF(billing_adjustments!E:E, B14, billing_adjustments!D:D) -> 182000 | E14: =SUMIF(collections!E:E, B14, collections!C:C) -> 100000 | F14: =E14 / C14 -> 0.47169811 | G14: =C14 - D14 -> 30000 | H14: =D14 - E14 -> 82000 | I14: =(C14 - D14) / C14 -> 0.14150943 | J14: =(D14 - E14) / D14 -> 0.45054945 | K14: =IF(F14>=0.85,"Healthy", IF(F14>=0.7,"Moderate Risk","High Risk")) -> High Risk | L14: 0.85
A15: Zenith Holdings | B15: 2 | C15: =SUMIF(time_entries!G:G, B15, time_entries!F:F) -> 182000 | D15: =C15 + SUMIF(billing_adjustments!E:E, B15, billing_adjustments!D:D) -> 152000 | E15: =SUMIF(collections!E:E, B15, collections!C:C) -> 100000 | F15: =E15 / C15 -> 0.54945055 | G15: =C15 - D15 -> 30000 | H15: =D15 - E15 -> 52000 | I15: =(C15 - D15) / C15 -> 0.16483516 | J15: =(D15 - E15) / D15 -> 0.34210526 | K15: =IF(F15>=0.85,"Healthy", IF(F15>=0.7,"Moderate Risk","High Risk")) -> High Risk | L15: 0.85
A16: Sharma Enterprises | B16: 3 | C16: =SUMIF(time_entries!G:G, B16, time_entries!F:F) -> 40000 | D16: =C16 + SUMIF(billing_adjustments!E:E, B16, billing_adjustments!D:D) -> 45000 | E16: =SUMIF(collections!E:E, B16, collections!C:C) -> 35000 | F16: =E16 / C16 -> 0.875 | G16: =C16 - D16 -> -5000 | H16: =D16 - E16 -> 10000 | I16: =(C16 - D16) / C16 -> -0.125 | J16: =(D16 - E16) / D16 -> 0.22222222 | K16: =IF(F16>=0.85,"Healthy", IF(F16>=0.7,"Moderate Risk","High Risk")) -> Healthy | L16: 0.85
A17: Global Retail Ltd | B17: 4 | C17: =SUMIF(time_entries!G:G, B17, time_entries!F:F) -> 49500 | D17: =C17 + SUMIF(billing_adjustments!E:E, B17, billing_adjustments!D:D) -> 34500 | E17: =SUMIF(collections!E:E, B17, collections!C:C) -> 30000 | F17: =E17 / C17 -> 0.60606061 | G17: =C17 - D17 -> 15000 | H17: =D17 - E17 -> 4500 | I17: =(C17 - D17) / C17 -> 0.3030303 | J17: =(D17 - E17) / D17 -> 0.13043478 | K17: =IF(F17>=0.85,"Healthy", IF(F17>=0.7,"Moderate Risk","High Risk")) -> High Risk | L17: 0.85
A18: Ramesh Kumar | B18: 5 | C18: =SUMIF(time_entries!G:G, B18, time_entries!F:F) -> 28500 | D18: =C18 + SUMIF(billing_adjustments!E:E, B18, billing_adjustments!D:D) -> 28500 | E18: =SUMIF(collections!E:E, B18, collections!C:C) -> 15000 | F18: =E18 / C18 -> 0.52631579 | G18: =C18 - D18 -> 0 | H18: =D18 - E18 -> 13500 | I18: =(C18 - D18) / C18 -> 0 | J18: =(D18 - E18) / D18 -> 0.47368421 | K18: =IF(F18>=0.85,"Healthy", IF(F18>=0.7,"Moderate Risk","High Risk")) -> High Risk | L18: 0.85
